<?xml version="1.0" encoding="utf-8"?>
<odoo>
  <data>

    <template id="assets_backend_extension" inherit_id="web.assets_backend">
      <xpath expr="." position="inside">
        <link rel="stylesheet" href="/smile_ci/static/src/css/kanban.css"/>
        <script type="text/javascript" src="/smile_ci/static/src/js/kanban.js"/>
        <link rel="stylesheet" href="/smile_ci/static/src/css/wizard.css"/>
        <script type="text/javascript" src="/smile_ci/static/src/js/wizard.js"/>
      </xpath>
    </template>

  </data>
</odoo>
